odoo/addons/auth_api_key_environment/README.rst
odoo/addons/auth_api_key_environment/__init__.py
odoo/addons/auth_api_key_environment/__manifest__.py
odoo/addons/auth_api_key_environment/i18n/auth_api_key_environment.pot
odoo/addons/auth_api_key_environment/models/__init__.py
odoo/addons/auth_api_key_environment/models/auth_api_key.py
odoo/addons/auth_api_key_environment/readme/CONFIGURE.rst
odoo/addons/auth_api_key_environment/readme/CONTRIBUTORS.rst
odoo/addons/auth_api_key_environment/readme/DESCRIPTION.rst
odoo/addons/auth_api_key_environment/static/description/icon.png
odoo/addons/auth_api_key_environment/static/description/index.html
odoo/addons/auth_api_key_environment/tests/__init__.py
odoo/addons/auth_api_key_environment/tests/test_auth_api_key.py
odoo12_addon_auth_api_key_environment-12.0.2.0.0.dist-info/METADATA
odoo12_addon_auth_api_key_environment-12.0.2.0.0.dist-info/WHEEL
odoo12_addon_auth_api_key_environment-12.0.2.0.0.dist-info/top_level.txt
odoo12_addon_auth_api_key_environment-12.0.2.0.0.dist-info/RECORD
