Metadata-Version: 2.1
Name: odoo12-addon-auth-api-key-environment
Version: 12.0.2.0.0
Summary: Use Server Environment for API Keys
Home-page: https://github.com/OCA/server-auth
Author: ACSONE SA/NV,Odoo Community Association (OCA)
Author-email: support@odoo-community.org
License: LGPL-3
Platform: UNKNOWN
Classifier: Programming Language :: Python
Classifier: Framework :: Odoo
Classifier: Framework :: Odoo :: 12.0
Classifier: License :: OSI Approved :: GNU Lesser General Public License v3 (LGPLv3)
Classifier: Development Status :: 4 - Beta
Requires-Python: >=3.5
Requires-Dist: odoo12-addon-auth-api-key
Requires-Dist: odoo12-addon-server-environment
Requires-Dist: odoo (<12.1dev,>=12.0a)
